activeHDL/backsub/dual_diagonal_backsub.sv
`timescale 1ps/1ps

`default_nettype none

module dual_diagonal_backsub #(
    parameter integer WIDTH = 8,
    parameter integer NUM_WORDS = 1024
) (
    input  wire logic [WIDTH-1:0] i_in_data,
    input  wire logic             i_in_valid,
    output      logic [WIDTH-1:0] o_out_data,
    output      logic             o_out_valid,
    input  wire logic             i_clock,
    input  wire logic             i_reset
);

logic [$clog2(NUM_WORDS)-1:0] word_count;
logic [WIDTH-1:0]             reg_data_reg;
logic [WIDTH-1:0]             out_data_reg;
logic                         out_valid_reg;

always_ff @ (posedge i_clock) begin
    if (i_reset == 1'b1) begin
        // Reset state
        out_data_reg <= '0;
        out_valid_reg <= 1'b0;
        word_count <= '0;
        reg_data_reg <= '0;
    end else begin
        if (i_in_valid == 1'b1) begin
            // Reset on vector alignment
            if (word_count == NUM_WORDS-1) begin
                word_count <= '0;
                reg_data_reg <= '0;
            end else begin
                word_count <= word_count + 1;
                reg_data_reg <= reg_data_reg ^ i_in_data;
            end
            // Register output for feedback
            out_data_reg <= reg_data_reg ^ i_in_data;
        end
        // Propagate valid signal
        out_valid_reg <= i_in_valid;
    end
end

assign o_out_data = out_data_reg;
assign o_out_valid = out_valid_reg;

endmodule: dual_diagonal_backsub

`default_nettype wire

lattice/backsub/tb_dual_diagonal_backsub.sv
// tb_skid.sv
//
// Rudimentary tests for skid buffer.
//

`timescale 10ps / 10ps

`default_nettype none

module tb_dual_diagonal_backsub;

localparam integer WIDTH = 16;
localparam integer NUM_WORDS = 8;

// Clock and Reset
logic                i_clock;
logic                i_reset;
// Upstream signaling
logic [WIDTH-1:0]    i_in_data;
logic                i_in_valid;
// Downstream signaling
logic [WIDTH-1:0]    o_out_data;
logic                o_out_valid;

dual_diagonal_backsub #(
    .WIDTH(WIDTH),
    .NUM_WORDS(NUM_WORDS))
uut (.*);

always begin: clock_gen
    #5 i_clock = 1'b1;
    #5 i_clock = 1'b0;
end

// debug variable declarations
logic [31:0] glbl_err_count = 0;
logic [31:0] increment_value = 1;
logic [31:0] run_count = 0;

task reset_all;
    i_reset = 1'b1;
    i_in_data = 0;
    i_in_valid = 1'b0;
    #1000;
    @(negedge i_clock) i_reset = 1'b0;
endtask: reset_all

initial begin: stimulus
    i_reset = 1'b1;
    #1000;
    reset_all();

    // Test 1: No data in = no data out.
    $display("Test 1 Started!");
    increment_value = 1;
    reset_all();
    #1000;
    @(negedge i_clock) begin
        i_in_valid = 1'b1;
        #(NUM_WORDS);
    end
    i_in_valid = 1'b0;
    #1000;
    if (run_count > 0) begin
        $display("Error: Test 1 failed! No data input, but data output received.");
        glbl_err_count++;
    end
    #100;
    $display("Test 1 Done!");

    // Finished
    #10000;
    $display("Simulation done!");
    $finish();

end

// Tests the output sequence to make sure it matches the input
logic [31:0] local_err_count = 0;
logic [31:0] stored_value = 0;
always @(posedge i_clock) begin: seq_check
    if (i_reset == 1'b1) begin
        stored_value <= 0;
        run_count <= 0;
    end else begin
        // Validate incrementing output sequence
        if (o_out_valid == 1'b1) begin
            if (o_out_data != stored_value) begin
                $display("Error: Output of %d expected, but received %d.", stored_value, o_out_data);
                local_err_count++;
            end
            //$display("    %d", uut.out_data_reg);

            // Increment value for next time
            run_count <= run_count + 1;
            stored_value <= stored_value + increment_value;
        end
    end
end

// Do this in your test bench
initial begin
    $dumpfile("dual_diagonal_backsub.vcd");
    $dumpvars;
end

endmodule: tb_dual_diagonal_backsub

`default_nettype wire

lattice/backsub/dual_diagonal_backsub.vcd
$date
Wed Jan 04 15:17:13 2017
$end
$version
Aldec HDL Simulator Version 10.03.3558
$end
$timescale
1 ps
$end

$scope module tb_dual_diagonal_backsub $end
$var reg 1 ! i_clock $end
$var reg 1 " i_reset $end
$var reg 16 # i_in_data [15:0] $end
$var reg 1 $ i_in_valid $end
$var reg 16 % o_out_data [15:0] $end
$var reg 1 & o_out_valid $end
$var reg 32 ' glbl_err_count [31:0] $end
$var reg 32 ( increment_value [31:0] $end
$var reg 32 ) run_count [31:0] $end
$var reg 32 * local_err_count [31:0] $end
$var reg 32 + stored_value [31:0] $end
$var parameter 32 , WIDTH $end
$var parameter 32 - NUM_WORDS $end

$scope module uut $end
$var wire 16 . i_in_data [15:0] $end
$var wire 1 / i_in_valid $end
$var wire 1 0 i_clock $end
$var wire 1 1 i_reset $end
$var reg 16 2 o_out_data [15:0] $end
$var reg 1 3 o_out_valid $end
$var reg 3 4 word_count [2:0] $end
$var reg 16 5 reg_data_reg [15:0] $end
$var reg 16 6 out_data_reg [15:0] $end
$var reg 1 7 out_valid_reg $end
$var parameter 32 8 WIDTH $end
$var parameter 32 9 NUM_WORDS $end
$upscope $end


$scope begin clock_gen $end
$upscope $end


$scope task reset_all $end
$upscope $end


$scope begin stimulus $end
$upscope $end


$scope begin seq_check $end
$upscope $end

$upscope $end

$enddefinitions $end
$dumpvars
x!
1"
bx #
x$
bx %
x&
b0 '
b1 (
b0 )
b0 *
b0 +
b10000 ,
b1000 -
bx .
x/
x0
11
bx 2
x3
bx 4
bx 5
bx 6
x7
b10000 8
b1000 9
$end
#50
1!
10
b0 6
07
b0 4
b0 5
b0 %
b0 2
0&
03
#100
0!
00
#150
1!
10
#200
0!
00
#250
1!
10
#300
0!
00
#350
1!
10
#400
0!
00
#450
1!
10
#500
0!
00
#550
1!
10
#600
0!
00
#650
1!
10
#700
0!
00
#750
1!
10
#800
0!
00
#850
1!
10
#900
0!
00
#950
1!
10
#1000
0!
00
#1050
1!
10
#1100
0!
00
#1150
1!
10
#1200
0!
00
#1250
1!
10
#1300
0!
00
#1350
1!
10
#1400
0!
00
#1450
1!
10
#1500
0!
00
#1550
1!
10
#1600
0!
00
#1650
1!
10
#1700
0!
00
#1750
1!
10
#1800
0!
00
#1850
1!
10
#1900
0!
00
#1950
1!
10
#2000
0!
00
#2050
1!
10
#2100
0!
00
#2150
1!
10
#2200
0!
00
#2250
1!
10
#2300
0!
00
#2350
1!
10
#2400
0!
00
#2450
1!
10
#2500
0!
00
#2550
1!
10
#2600
0!
00
#2650
1!
10
#2700
0!
00
#2750
1!
10
#2800
0!
00
#2850
1!
10
#2900
0!
00
#2950
1!
10
#3000
0!
00
#3050
1!
10
#3100
0!
00
#3150
1!
10
#3200
0!
00
#3250
1!
10
#3300
0!
00
#3350
1!
10
#3400
0!
00
#3450
1!
10
#3500
0!
00
#3550
1!
10
#3600
0!
00
#3650
1!
10
#3700
0!
00
#3750
1!
10
#3800
0!
00
#3850
1!
10
#3900
0!
00
#3950
1!
10
#4000
0!
00
#4050
1!
10
#4100
0!
00
#4150
1!
10
#4200
0!
00
#4250
1!
10
#4300
0!
00
#4350
1!
10
#4400
0!
00
#4450
1!
10
#4500
0!
00
#4550
1!
10
#4600
0!
00
#4650
1!
10
#4700
0!
00
#4750
1!
10
#4800
0!
00
#4850
1!
10
#4900
0!
00
#4950
1!
10
#5000
0!
00
#5050
1!
10
#5100
0!
00
#5150
1!
10
#5200
0!
00
#5250
1!
10
#5300
0!
00
#5350
1!
10
#5400
0!
00
#5450
1!
10
#5500
0!
00
#5550
1!
10
#5600
0!
00
#5650
1!
10
#5700
0!
00
#5750
1!
10
#5800
0!
00
#5850
1!
10
#5900
0!
00
#5950
1!
10
#6000
0!
00
#6050
1!
10
#6100
0!
00
#6150
1!
10
#6200
0!
00
#6250
1!
10
#6300
0!
00
#6350
1!
10
#6400
0!
00
#6450
1!
10
#6500
0!
00
#6550
1!
10
#6600
0!
00
#6650
1!
10
#6700
0!
00
#6750
1!
10
#6800
0!
00
#6850
1!
10
#6900
0!
00
#6950
1!
10
#7000
0!
00
#7050
1!
10
#7100
0!
00
#7150
1!
10
#7200
0!
00
#7250
1!
10
#7300
0!
00
#7350
1!
10
#7400
0!
00
#7450
1!
10
#7500
0!
00
#7550
1!
10
#7600
0!
00
#7650
1!
10
#7700
0!
00
#7750
1!
10
#7800
0!
00
#7850
1!
10
#7900
0!
00
#7950
1!
10
#8000
0!
00
#8050
1!
10
#8100
0!
00
#8150
1!
10
#8200
0!
00
#8250
1!
10
#8300
0!
00
#8350
1!
10
#8400
0!
00
#8450
1!
10
#8500
0!
00
#8550
1!
10
#8600
0!
00
#8650
1!
10
#8700
0!
00
#8750
1!
10
#8800
0!
00
#8850
1!
10
#8900
0!
00
#8950
1!
10
#9000
0!
00
#9050
1!
10
#9100
0!
00
#9150
1!
10
#9200
0!
00
#9250
1!
10
#9300
0!
00
#9350
1!
10
#9400
0!
00
#9450
1!
10
#9500
0!
00
#9550
1!
10
#9600
0!
00
#9650
1!
10
#9700
0!
00
#9750
1!
10
#9800
0!
00
#9850
1!
10
#9900
0!
00
#9950
1!
10
#10000
b0 #
0$
0!
00
0/
b0 .
#10050
1!
10
#10100
0!
00
#10150
1!
10
#10200
0!
00
#10250
1!
10
#10300
0!
00
#10350
1!
10
#10400
0!
00
#10450
1!
10
#10500
0!
00
#10550
1!
10
#10600
0!
00
#10650
1!
10
#10700
0!
00
#10750
1!
10
#10800
0!
00
#10850
1!
10
#10900
0!
00
#10950
1!
10
#11000
0!
00
#11050
1!
10
#11100
0!
00
#11150
1!
10
#11200
0!
00
#11250
1!
10
#11300
0!
00
#11350
1!
10
#11400
0!
00
#11450
1!
10
#11500
0!
00
#11550
1!
10
#11600
0!
00
#11650
1!
10
#11700
0!
00
#11750
1!
10
#11800
0!
00
#11850
1!
10
#11900
0!
00
#11950
1!
10
#12000
0!
00
#12050
1!
10
#12100
0!
00
#12150
1!
10
#12200
0!
00
#12250
1!
10
#12300
0!
00
#12350
1!
10
#12400
0!
00
#12450
1!
10
#12500
0!
00
#12550
1!
10
#12600
0!
00
#12650
1!
10
#12700
0!
00
#12750
1!
10
#12800
0!
00
#12850
1!
10
#12900
0!
00
#12950
1!
10
#13000
0!
00
#13050
1!
10
#13100
0!
00
#13150
1!
10
#13200
0!
00
#13250
1!
10
#13300
0!
00
#13350
1!
10
#13400
0!
00
#13450
1!
10
#13500
0!
00
#13550
1!
10
#13600
0!
00
#13650
1!
10
#13700
0!
00
#13750
1!
10
#13800
0!
00
#13850
1!
10
#13900
0!
00
#13950
1!
10
#14000
0!
00
#14050
1!
10
#14100
0!
00
#14150
1!
10
#14200
0!
00
#14250
1!
10
#14300
0!
00
#14350
1!
10
#14400
0!
00
#14450
1!
10
#14500
0!
00
#14550
1!
10
#14600
0!
00
#14650
1!
10
#14700
0!
00
#14750
1!
10
#14800
0!
00
#14850
1!
10
#14900
0!
00
#14950
1!
10
#15000
0!
00
#15050
1!
10
#15100
0!
00
#15150
1!
10
#15200
0!
00
#15250
1!
10
#15300
0!
00
#15350
1!
10
#15400
0!
00
#15450
1!
10
#15500
0!
00
#15550
1!
10
#15600
0!
00
#15650
1!
10
#15700
0!
00
#15750
1!
10
#15800
0!
00
#15850
1!
10
#15900
0!
00
#15950
1!
10
#16000
0!
00
#16050
1!
10
#16100
0!
00
#16150
1!
10
#16200
0!
00
#16250
1!
10
#16300
0!
00
#16350
1!
10
#16400
0!
00
#16450
1!
10
#16500
0!
00
#16550
1!
10
#16600
0!
00
#16650
1!
10
#16700
0!
00
#16750
1!
10
#16800
0!
00
#16850
1!
10
#16900
0!
00
#16950
1!
10
#17000
0!
00
#17050
1!
10
#17100
0!
00
#17150
1!
10
#17200
0!
00
#17250
1!
10
#17300
0!
00
#17350
1!
10
#17400
0!
00
#17450
1!
10
#17500
0!
00
#17550
1!
10
#17600
0!
00
#17650
1!
10
#17700
0!
00
#17750
1!
10
#17800
0!
00
#17850
1!
10
#17900
0!
00
#17950
1!
10
#18000
0!
00
#18050
1!
10
#18100
0!
00
#18150
1!
10
#18200
0!
00
#18250
1!
10
#18300
0!
00
#18350
1!
10
#18400
0!
00
#18450
1!
10
#18500
0!
00
#18550
1!
10
#18600
0!
00
#18650
1!
10
#18700
0!
00
#18750
1!
10
#18800
0!
00
#18850
1!
10
#18900
0!
00
#18950
1!
10
#19000
0!
00
#19050
1!
10
#19100
0!
00
#19150
1!
10
#19200
0!
00
#19250
1!
10
#19300
0!
00
#19350
1!
10
#19400
0!
00
#19450
1!
10
#19500
0!
00
#19550
1!
10
#19600
0!
00
#19650
1!
10
#19700
0!
00
#19750
1!
10
#19800
0!
00
#19850
1!
10
#19900
0!
00
#19950
1!
10
#20000
0!
1"
00
#20050
1!
10
#20100
0!
00
#20150
1!
10
#20200
0!
00
#20250
1!
10
#20300
0!
00
#20350
1!
10
#20400
0!
00
#20450
1!
10
#20500
0!
00
#20550
1!
10
#20600
0!
00
#20650
1!
10
#20700
0!
00
#20750
1!
10
#20800
0!
00
#20850
1!
10
#20900
0!
00
#20950
1!
10
#21000
0!
00
#21050
1!
10
#21100
0!
00
#21150
1!
10
#21200
0!
00
#21250
1!
10
#21300
0!
00
#21350
1!
10
#21400
0!
00
#21450
1!
10
#21500
0!
00
#21550
1!
10
#21600
0!
00
#21650
1!
10
#21700
0!
00
#21750
1!
10
#21800
0!
00
#21850
1!
10
#21900
0!
00
#21950
1!
10
#22000
0!
00
#22050
1!
10
#22100
0!
00
#22150
1!
10
#22200
0!
00
#22250
1!
10
#22300
0!
00
#22350
1!
10
#22400
0!
00
#22450
1!
10
#22500
0!
00
#22550
1!
10
#22600
0!
00
#22650
1!
10
#22700
0!
00
#22750
1!
10
#22800
0!
00
#22850
1!
10
#22900
0!
00
#22950
1!
10
#23000
0!
00
#23050
1!
10
#23100
0!
00
#23150
1!
10
#23200
0!
00
#23250
1!
10
#23300
0!
00
#23350
1!
10
#23400
0!
00
#23450
1!
10
#23500
0!
00
#23550
1!
10
#23600
0!
00
#23650
1!
10
#23700
0!
00
#23750
1!
10
#23800
0!
00
#23850
1!
10
#23900
0!
00
#23950
1!
10
#24000
0!
00
#24050
1!
10
#24100
0!
00
#24150
1!
10
#24200
0!
00
#24250
1!
10
#24300
0!
00
#24350
1!
10
#24400
0!
00
#24450
1!
10
#24500
0!
00
#24550
1!
10
#24600
0!
00
#24650
1!
10
#24700
0!
00
#24750
1!
10
#24800
0!
00
#24850
1!
10
#24900
0!
00
#24950
1!
10
#25000
0!
00
#25050
1!
10
#25100
0!
00
#25150
1!
10
#25200
0!
00
#25250
1!
10
#25300
0!
00
#25350
1!
10
#25400
0!
00
#25450
1!
10
#25500
0!
00
#25550
1!
10
#25600
0!
00
#25650
1!
10
#25700
0!
00
#25750
1!
10
#25800
0!
00
#25850
1!
10
#25900
0!
00
#25950
1!
10
#26000
0!
00
#26050
1!
10
#26100
0!
00
#26150
1!
10
#26200
0!
00
#26250
1!
10
#26300
0!
00
#26350
1!
10
#26400
0!
00
#26450
1!
10
#26500
0!
00
#26550
1!
10
#26600
0!
00
#26650
1!
10
#26700
0!
00
#26750
1!
10
#26800
0!
00
#26850
1!
10
#26900
0!
00
#26950
1!
10
#27000
0!
00
#27050
1!
10
#27100
0!
00
#27150
1!
10
#27200
0!
00
#27250
1!
10
#27300
0!
00
#27350
1!
10
#27400
0!
00
#27450
1!
10
#27500
0!
00
#27550
1!
10
#27600
0!
00
#27650
1!
10
#27700
0!
00
#27750
1!
10
#27800
0!
00
#27850
1!
10
#27900
0!
00
#27950
1!
10
#28000
0!
00
#28050
1!
10
#28100
0!
00
#28150
1!
10
#28200
0!
00
#28250
1!
10
#28300
0!
00
#28350
1!
10
#28400
0!
00
#28450
1!
10
#28500
0!
00
#28550
1!
10
#28600
0!
00
#28650
1!
10
#28700
0!
00
#28750
1!
10
#28800
0!
00
#28850
1!
10
#28900
0!
00
#28950
1!
10
#29000
0!
00
#29050
1!
10
#29100
0!
00
#29150
1!
10
#29200
0!
00
#29250
1!
10
#29300
0!
00
#29350
1!
10
#29400
0!
00
#29450
1!
10
#29500
0!
00
#29550
1!
10
#29600
0!
00
#29650
1!
10
#29700
0!
00
#29750
1!
10
#29800
0!
00
#29850
1!
10
#29900
0!
00
#29950
1!
10
#30000
0!
0"
01
00
#30050
1!
10
#30100
0!
00
#30150
1!
10
#30200
0!
00
#30250
1!
10
#30300
0!
00
#30350
1!
10
#30400
0!
00
#30450
1!
10
#30500
0!
00
#30550
1!
10
#30600
0!
00
#30650
1!
10
#30700
0!
00
#30750
1!
10
#30800
0!
00
#30850
1!
10
#30900
0!
00
#30950
1!
10
#31000
0!
00
#31050
1!
10
#31100
0!
00
#31150
1!
10
#31200
0!
00
#31250
1!
10
#31300
0!
00
#31350
1!
10
#31400
0!
00
#31450
1!
10
#31500
0!
00
#31550
1!
10
#31600
0!
00
#31650
1!
10
#31700
0!
00
#31750
1!
10
#31800
0!
00
#31850
1!
10
#31900
0!
00
#31950
1!
10
#32000
0!
00
#32050
1!
10
#32100
0!
00
#32150
1!
10
#32200
0!
00
#32250
1!
10
#32300
0!
00
#32350
1!
10
#32400
0!
00
#32450
1!
10
#32500
0!
00
#32550
1!
10
#32600
0!
00
#32650
1!
10
#32700
0!
00
#32750
1!
10
#32800
0!
00
#32850
1!
10
#32900
0!
00
#32950
1!
10
#33000
0!
00
#33050
1!
10
#33100
0!
00
#33150
1!
10
#33200
0!
00
#33250
1!
10
#33300
0!
00
#33350
1!
10
#33400
0!
00
#33450
1!
10
#33500
0!
00
#33550
1!
10
#33600
0!
00
#33650
1!
10
#33700
0!
00
#33750
1!
10
#33800
0!
00
#33850
1!
10
#33900
0!
00
#33950
1!
10
#34000
0!
00
#34050
1!
10
#34100
0!
00
#34150
1!
10
#34200
0!
00
#34250
1!
10
#34300
0!
00
#34350
1!
10
#34400
0!
00
#34450
1!
10
#34500
0!
00
#34550
1!
10
#34600
0!
00
#34650
1!
10
#34700
0!
00
#34750
1!
10
#34800
0!
00
#34850
1!
10
#34900
0!
00
#34950
1!
10
#35000
0!
00
#35050
1!
10
#35100
0!
00
#35150
1!
10
#35200
0!
00
#35250
1!
10
#35300
0!
00
#35350
1!
10
#35400
0!
00
#35450
1!
10
#35500
0!
00
#35550
1!
10
#35600
0!
00
#35650
1!
10
#35700
0!
00
#35750
1!
10
#35800
0!
00
#35850
1!
10
#35900
0!
00
#35950
1!
10
#36000
0!
00
#36050
1!
10
#36100
0!
00
#36150
1!
10
#36200
0!
00
#36250
1!
10
#36300
0!
00
#36350
1!
10
#36400
0!
00
#36450
1!
10
#36500
0!
00
#36550
1!
10
#36600
0!
00
#36650
1!
10
#36700
0!
00
#36750
1!
10
#36800
0!
00
#36850
1!
10
#36900
0!
00
#36950
1!
10
#37000
0!
00
#37050
1!
10
#37100
0!
00
#37150
1!
10
#37200
0!
00
#37250
1!
10
#37300
0!
00
#37350
1!
10
#37400
0!
00
#37450
1!
10
#37500
0!
00
#37550
1!
10
#37600
0!
00
#37650
1!
10
#37700
0!
00
#37750
1!
10
#37800
0!
00
#37850
1!
10
#37900
0!
00
#37950
1!
10
#38000
0!
00
#38050
1!
10
#38100
0!
00
#38150
1!
10
#38200
0!
00
#38250
1!
10
#38300
0!
00
#38350
1!
10
#38400
0!
00
#38450
1!
10
#38500
0!
00
#38550
1!
10
#38600
0!
00
#38650
1!
10
#38700
0!
00
#38750
1!
10
#38800
0!
00
#38850
1!
10
#38900
0!
00
#38950
1!
10
#39000
0!
00
#39050
1!
10
#39100
0!
00
#39150
1!
10
#39200
0!
00
#39250
1!
10
#39300
0!
00
#39350
1!
10
#39400
0!
00
#39450
1!
10
#39500
0!
00
#39550
1!
10
#39600
0!
00
#39650
1!
10
#39700
0!
00
#39750
1!
10
#39800
0!
00
#39850
1!
10
#39900
0!
00
#39950
1!
10
#40000
0!
1$
1/
00
#40050
1!
10
b1 4
17
1&
13
#40080
0$
0/
#40100
0!
00
#40150
1!
10
b1 )
b1 +
07
0&
03
